zizou/__init__.py
zizou/anomaly_base.py
zizou/autoencoder.py
zizou/cpxtrace.py
zizou/data.py
zizou/dsar.py
zizou/feature_base.py
zizou/pca.py
zizou/rsam.py
zizou/sandbox.ipynb
zizou/spectral_features.py
zizou/ssam.py
zizou/util.py
zizou/visualise.py
zizou/zizou_logging.py
zizou/package_data/config.yml
zizou/package_data/index.html
zizou-0.1.3.dist-info/METADATA
zizou-0.1.3.dist-info/WHEEL
zizou-0.1.3.dist-info/licenses/LICENSE
zizou-0.1.3.dist-info/RECORD
