Metadata-Version: 2.3
Name: zizou
Version: 0.1.3
Summary: Python package to detect anomalies in geoscience time series data
Project-URL: Homepage, https://tsc-tools.github.io/zizou/
Project-URL: Issues, https://github.com/tsc-tools/zizou/issues
Author-email: Yannik Behr <y.behr@gns.cri.nz>, Christof Mueller <c.mueller@gns.cri.nz>
License: GPL v3
Classifier: License :: OSI Approved :: GNU General Public License v3 (GPLv3)
Classifier: Operating System :: OS Independent
Classifier: Programming Language :: Python :: 3
Requires-Python: >=3.7
Requires-Dist: boto3
Requires-Dist: numpy
Requires-Dist: obspy
Requires-Dist: pandas
Requires-Dist: pyyaml
Requires-Dist: scipy
Requires-Dist: tonik
Requires-Dist: tqdm
Requires-Dist: xarray[io]
Provides-Extra: ml
Requires-Dist: scikit-fuzzy; extra == 'ml'
Requires-Dist: scikit-learn; extra == 'ml'
Requires-Dist: torch; extra == 'ml'
Requires-Dist: torchaudio; extra == 'ml'
Requires-Dist: torchvision; extra == 'ml'
